solver/__init__.py
solver/cartesian_mesh.py
solver/cartesian_solver.py
solver/mesher.py
solver/py.typed
solver/solver.py
solver/utilities.py
solver/code_project/__init__.py
solver/code_project/main.py
bray_pde-0.1.4.dist-info/LICENSE
bray_pde-0.1.4.dist-info/METADATA
bray_pde-0.1.4.dist-info/WHEEL
bray_pde-0.1.4.dist-info/top_level.txt
bray_pde-0.1.4.dist-info/RECORD
